max_char_match/__init__.py
max_char_match/alignment.py
max_char_match/version.py
max_char_match-1.3.1.dist-info/WHEEL
max_char_match-1.3.1.dist-info/METADATA
max_char_match-1.3.1.dist-info/RECORD
