Metadata-Version: 2.1
Name: max-char-match
Version: 1.3.1
Summary: MaxCharMatch metric
Author: melisa-writer
Author-email: melisa@writer.com
Requires-Python: >=3.8,<4.0
Classifier: Programming Language :: Python :: 3
Classifier: Programming Language :: Python :: 3.10
Classifier: Programming Language :: Python :: 3.8
Classifier: Programming Language :: Python :: 3.9
Requires-Dist: datasets (>=2.1.0,<3.0.0)
Requires-Dist: diff-match-patch (>=20200713,<20200714)
Requires-Dist: more-itertools (>=8.12.0,<9.0.0)
Requires-Dist: numpy (>=1.22.3,<2.0.0)
Requires-Dist: tqdm (>=4.64.0,<5.0.0)
